exavault/__init__.py
exavault/api_client.py
exavault/configuration.py
exavault/rest.py
exavault/api/__init__.py
exavault/api/account_api.py
exavault/api/activity_api.py
exavault/api/email_api.py
exavault/api/email_lists_api.py
exavault/api/form_api.py
exavault/api/notifications_api.py
exavault/api/recipients_api.py
exavault/api/resources_api.py
exavault/api/shares_api.py
exavault/api/ssh_keys_api.py
exavault/api/users_api.py
exavault/api/webhooks_api.py
exavault/models/__init__.py
exavault/models/access_mode.py
exavault/models/account.py
exavault/models/account_allowed_ip_ranges.py
exavault/models/account_attributes.py
exavault/models/account_attributes_allowed_ip.py
exavault/models/account_quota_values.py
exavault/models/account_response.py
exavault/models/add_email_list_request_body.py
exavault/models/add_folder_request_body.py
exavault/models/add_notification_request_body.py
exavault/models/add_share_request_body.py
exavault/models/add_ssh_key_request_body.py
exavault/models/add_user_request_body.py
exavault/models/add_webhook_request_body.py
exavault/models/any_of_notification_collection_response_included_items.py
exavault/models/any_of_notification_response_included_items.py
exavault/models/any_of_resource_collection_response_included_items.py
exavault/models/any_of_resource_multi_response_responses_items.py
exavault/models/any_of_resource_response_included_items.py
exavault/models/any_of_share_collection_response_included_items.py
exavault/models/any_of_share_response_included_items.py
exavault/models/any_of_user_collection_response_included_items.py
exavault/models/any_of_user_response_included_items.py
exavault/models/any_of_webhook_collection_response_included_items.py
exavault/models/any_of_webhook_response_included_items.py
exavault/models/branding_settings.py
exavault/models/branding_settings_values.py
exavault/models/compress_files_request_body.py
exavault/models/copy_resources_request_body.py
exavault/models/delete_resources_request_body.py
exavault-2.1.6.dist-info/LICENSE
exavault-2.1.6.dist-info/METADATA
exavault-2.1.6.dist-info/WHEEL
exavault-2.1.6.dist-info/top_level.txt
exavault-2.1.6.dist-info/RECORD
