Metadata-Version: 2.1
Name: exavault
Version: 2.1.6
Summary: Python SDK for interacting with ExaVault API
Home-page: https://github.com/exavault/evapi-python
Author-email: support@exavault.com
License: UNKNOWN
Project-URL: API Reference, https://www.exavault.com/developer/api-docs/
Project-URL: Contact Support, https://www.exavault.com/contact/
Project-URL: Source, https://github.com/ExaVault/evapi-python/
Keywords: api,exavault,development
Platform: UNKNOWN
Classifier: Development Status :: 5 - Production/Stable
Classifier: Intended Audience :: Developers
Classifier: Topic :: Software Development :: Libraries
Classifier: License :: OSI Approved :: MIT License
Classifier: Programming Language :: Python :: 3
Classifier: Programming Language :: Python :: 3.5
Classifier: Programming Language :: Python :: 3.6
Classifier: Programming Language :: Python :: 3.7
Classifier: Programming Language :: Python :: 3.8
Classifier: Programming Language :: Python :: 2.7
Requires-Python: >=2.7, !=3.0.*, !=3.1.*, !=3.2.*, !=3.3.*, <4
Requires-Dist: certifi
Requires-Dist: python-dateutil (<3.0,>=2.5.3)
Requires-Dist: python-dotenv
Requires-Dist: setuptools (>=21.0.0)
Requires-Dist: six (>=1.10)
Requires-Dist: urllib3 (>=1.15.1)
